README.rst
pical.py
setup.py
pical.egg-info/PKG-INFO
pical.egg-info/SOURCES.txt
pical.egg-info/dependency_links.txt
pical.egg-info/top_level.txt