Metadata-Version: 1.0
Name: pical
Version: 0.3
Summary: icalendar parser,builder library with query function
Home-page: https://github.com/hkwi/pical
Author: Hiroaki KAWAI
Author-email: hiroaki.kawai+pypi@gmail.com
License: UNKNOWN
Platform: UNKNOWN
